moff_cli/__init__.py
moff_cli/__main__.py
moff_cli/__version__.py
moff_cli/cli.py
moff_cli/py.typed
moff_cli/check/__init__.py
moff_cli/check/check.py
moff_cli/check/fixer.py
moff_cli/collector/__init__.py
moff_cli/collector/collector.py
moff_cli/settings/__init__.py
moff_cli/settings/settings.py
moff_cli/tree/__init__.py
moff_cli/tree/tree.py
moff_cli-0.3.1.dist-info/METADATA
moff_cli-0.3.1.dist-info/WHEEL
moff_cli-0.3.1.dist-info/entry_points.txt
moff_cli-0.3.1.dist-info/licenses/LICENSE
moff_cli-0.3.1.dist-info/RECORD
