Metadata-Version: 2.4
Name: moff-cli
Version: 0.3.1
Summary: MOFF - Markdown Organization and Format Framework. A CLI tool for validating documentation structure.
Project-URL: Homepage, https://github.com/lennartpollvogt/moff-cli
Project-URL: Documentation, https://github.com/lennartpollvogt/moff-cli#readme
Project-URL: Repository, https://github.com/lennartpollvogt/moff-cli
Project-URL: Issues, https://github.com/lennartpollvogt/moff-cli/issues
Author-email: Lennart Pollvogt <lennartpollvogt@protonmail.com>
License: MIT
License-File: LICENSE
Keywords: cli,documentation,linting,markdown,validation
Classifier: Development Status :: 3 - Alpha
Classifier: Environment :: Console
Classifier: Intended Audience :: Developers
Classifier: License :: OSI Approved :: MIT License
Classifier: Programming Language :: Python :: 3
Classifier: Programming Language :: Python :: 3.12
Classifier: Topic :: Documentation
Classifier: Topic :: Software Development :: Documentation
Classifier: Topic :: Software Development :: Quality Assurance
Classifier: Topic :: Text Processing :: Markup :: Markdown
Requires-Python: >=3.12
Requires-Dist: markdown-to-data>=2.0.0
Requires-Dist: pyyaml>=6.0.2
Requires-Dist: rich>=14.1.0
Provides-Extra: dev
Requires-Dist: black>=23.0.0; extra == 'dev'
Requires-Dist: pytest-cov>=4.0.0; extra == 'dev'
Requires-Dist: pytest>=7.0.0; extra == 'dev'
Requires-Dist: ruff>=0.1.0; extra == 'dev'
